LICENSE
MANIFEST.in
README.rst
setup.cfg
setup.py
versioneer.py
pele_platform/__init__.py
pele_platform/_version.py
pele_platform/converter.py
pele_platform/main.py
pele_platform/pathway_extractor.py
pele_platform/plotter.py
pele_platform.egg-info/PKG-INFO
pele_platform.egg-info/SOURCES.txt
pele_platform.egg-info/dependency_links.txt
pele_platform.egg-info/requires.txt
pele_platform.egg-info/top_level.txt
pele_platform/Adaptive/__init__.py
pele_platform/Adaptive/box.py
pele_platform/Adaptive/interaction_restrictions.py
pele_platform/Adaptive/metrics.py
pele_platform/Adaptive/parametrizer.py
pele_platform/Adaptive/pca.py
pele_platform/Adaptive/plop_ligand_parametrization.py
pele_platform/Adaptive/plop_solvent.py
pele_platform/Adaptive/preequilibrator.py
pele_platform/Adaptive/simulation.py
pele_platform/Checker/__init__.py
pele_platform/Checker/environment_variables.py
pele_platform/Checker/executable.py
pele_platform/Checker/main.py
pele_platform/Checker/pdb_checker.py
pele_platform/Checker/python_version.py
pele_platform/Checker/valid_flags.py
pele_platform/Errors/__init__.py
pele_platform/Errors/custom_errors.py
pele_platform/Examples/test.sl
pele_platform/Examples/Adaptive/STR.rot.assign
pele_platform/Examples/Adaptive/adaptive.conf
pele_platform/Examples/Adaptive/pele_file_4Adaptive.conf
pele_platform/Examples/Adaptive/strz
pele_platform/Examples/Adaptive/test.sl
pele_platform/Examples/Msm/AS4_INIT.mae
pele_platform/Examples/Msm/PR_1A28_protein.pdb
pele_platform/Examples/Msm/PR_1A28_xray_-_minimized.pdb
pele_platform/Examples/Msm/PR_1A28_xray_-_minimized_processed.pdb
pele_platform/Examples/Msm/PR_AS4.pdb
pele_platform/Examples/Msm/input.yaml
pele_platform/Examples/PPI/1f47_ligand.pdb
pele_platform/Examples/PPI/1f47_prep.pdb
pele_platform/Examples/PPI/1tnf_ligand.pdb
pele_platform/Examples/PPI/1tnf_prep.pdb
pele_platform/Examples/PPI/input.yaml
pele_platform/Examples/PPI/input_folder.yaml
pele_platform/Examples/PPI/input_skipref.yaml
pele_platform/Examples/RNA/2l94.yaml
pele_platform/Examples/RNA/5C45_prep.pdb
pele_platform/Examples/RNA/5C45_prep_proc.pdb
pele_platform/Examples/RNA/input.yaml
pele_platform/Examples/RNA/input_induced.yaml
