Metadata-Version: 2.1
Name: pele-platform
Version: 1.6.3
Summary: Automatic platform to launch PELE simulations
Home-page: https://github.com/NostrumBioDiscovery/pele_platform
Author: Nostrum Biodiscovery
Author-email: pelesupport@nostrumbiodiscovery.com
License: UNKNOWN
Platform: UNKNOWN
License-File: LICENSE
